WeiXueyuanNginxJiaocheng/README.md
WeiXueyuanNginxJiaocheng/__init__.py
WeiXueyuanNginxJiaocheng/__main__.py
WeiXueyuanNginxJiaocheng/file.epub
WeiXueyuanNginxJiaocheng/index.html
WeiXueyuanNginxJiaocheng/css/__init__.py
WeiXueyuanNginxJiaocheng/css/annotations.css
WeiXueyuanNginxJiaocheng/css/main.css
WeiXueyuanNginxJiaocheng/css/normalize.css
WeiXueyuanNginxJiaocheng/css/popup.css
WeiXueyuanNginxJiaocheng/font/__init__.py
WeiXueyuanNginxJiaocheng/font/fontello.eot
WeiXueyuanNginxJiaocheng/font/fontello.svg
WeiXueyuanNginxJiaocheng/font/fontello.ttf
WeiXueyuanNginxJiaocheng/font/fontello.woff
WeiXueyuanNginxJiaocheng/img/__init__.py
WeiXueyuanNginxJiaocheng/img/annotator-glyph-sprite.png
WeiXueyuanNginxJiaocheng/img/annotator-icon-sprite.png
WeiXueyuanNginxJiaocheng/img/apple-touch-icon.png
WeiXueyuanNginxJiaocheng/img/cancelfullscreen.png
WeiXueyuanNginxJiaocheng/img/close.png
WeiXueyuanNginxJiaocheng/img/fullscreen.png
WeiXueyuanNginxJiaocheng/img/loader.gif
WeiXueyuanNginxJiaocheng/img/menu-icon.png
WeiXueyuanNginxJiaocheng/img/save.png
WeiXueyuanNginxJiaocheng/img/saved.png
WeiXueyuanNginxJiaocheng/img/settings-s.png
WeiXueyuanNginxJiaocheng/img/settings.png
WeiXueyuanNginxJiaocheng/img/star.png
WeiXueyuanNginxJiaocheng/js/__init__.py
WeiXueyuanNginxJiaocheng/js/epub.js
WeiXueyuanNginxJiaocheng/js/epub.min.js
WeiXueyuanNginxJiaocheng/js/epub.min.map
WeiXueyuanNginxJiaocheng/js/hooks.min.js
WeiXueyuanNginxJiaocheng/js/hooks.min.map
WeiXueyuanNginxJiaocheng/js/reader.js
WeiXueyuanNginxJiaocheng/js/reader.js.map
WeiXueyuanNginxJiaocheng/js/reader.min.js
WeiXueyuanNginxJiaocheng/js/reader.min.map
WeiXueyuanNginxJiaocheng/js/hooks/__init__.py
WeiXueyuanNginxJiaocheng/js/hooks/extensions/__init__.py
WeiXueyuanNginxJiaocheng/js/hooks/extensions/highlight.js
WeiXueyuanNginxJiaocheng/js/libs/__init__.py
WeiXueyuanNginxJiaocheng/js/libs/jquery.min.js
WeiXueyuanNginxJiaocheng/js/libs/localforage.min.js
WeiXueyuanNginxJiaocheng/js/libs/screenfull.js
wei_xueyuan_nginx_jiaocheng-2024.3.6.0.dist-info/METADATA
wei_xueyuan_nginx_jiaocheng-2024.3.6.0.dist-info/WHEEL
wei_xueyuan_nginx_jiaocheng-2024.3.6.0.dist-info/entry_points.txt
wei_xueyuan_nginx_jiaocheng-2024.3.6.0.dist-info/top_level.txt
wei_xueyuan_nginx_jiaocheng-2024.3.6.0.dist-info/RECORD
